Metadata-Version: 2.1
Name: doctable
Version: 2.0
Summary: Simple database interface for text analysis applications.
Home-page: https://github.com/devincornell/doctable
Download-URL: https://github.com/devincornell/doctable/archive/v2.0.tar.gz
Author: Devin J. Cornell
Author-email: devinj.cornell@gmail.com
License: MIT
License-File: LICENSE.txt
Requires-Dist: setuptools
Requires-Dist: sqlalchemy >=2.0
Requires-Dist: pandas
Requires-Dist: numpy
Requires-Dist: pymongo
